grafi_dev/cli.py
grafi_dev/server.py
grafi_dev/frontend/index.html
grafi_dev-0.0.9.dist-info/licenses/LICENSE
grafi_dev-0.0.9.dist-info/METADATA
grafi_dev-0.0.9.dist-info/WHEEL
grafi_dev-0.0.9.dist-info/entry_points.txt
grafi_dev-0.0.9.dist-info/top_level.txt
grafi_dev-0.0.9.dist-info/RECORD
