Metadata-Version: 2.4
Name: grafi-dev
Version: 0.0.9
Summary: Run a grafi Assistant locally with a live workflow graph & trace viewer
Author-email: Craig Li <craig@binome.dev>
Requires-Python: >=3.11
License-File: LICENSE
Requires-Dist: fastapi>=0.115.12
Requires-Dist: grafi>=0.0.31
Requires-Dist: typer>=0.15.3
Requires-Dist: uvicorn>=0.34.2
Dynamic: license-file
